django_pdf/__init__.py
django_pdf/admin.py
django_pdf/apps.py
django_pdf/tests.py
django_pdf/urls.py
django_pdf/version.py
django_pdf/views.py
django_pdf/templates/pdf/din5008.rml
django_pdf/templates/pdf/hello.rml
django_z3c.rml-0.1.dist-info/METADATA
django_z3c.rml-0.1.dist-info/WHEEL
django_z3c.rml-0.1.dist-info/top_level.txt
django_z3c.rml-0.1.dist-info/RECORD
